MANIFEST.in
README.txt
setup.cfg
setup.py
collective/__init__.py
collective.cdn.coral.egg-info/PKG-INFO
collective.cdn.coral.egg-info/SOURCES.txt
collective.cdn.coral.egg-info/dependency_links.txt
collective.cdn.coral.egg-info/entry_points.txt
collective.cdn.coral.egg-info/namespace_packages.txt
collective.cdn.coral.egg-info/not-zip-safe
collective.cdn.coral.egg-info/requires.txt
collective.cdn.coral.egg-info/top_level.txt
collective/cdn/__init__.py
collective/cdn/coral/README.txt
collective/cdn/coral/__init__.py
collective/cdn/coral/config.py
collective/cdn/coral/configure.zcml
collective/cdn/coral/provider.py
collective/cdn/coral/tests.py
collective/cdn/coral/version.txt
collective/cdn/coral/docs/__init__.py
collective/cdn/coral/docs/browser.txt
docs/HISTORY.txt
docs/INSTALL.txt
docs/LICENSE.GPL
docs/LICENSE.txt